odoo/addons/shopfloor_reception_purchase_partner_ref/README.rst
odoo/addons/shopfloor_reception_purchase_partner_ref/__init__.py
odoo/addons/shopfloor_reception_purchase_partner_ref/__manifest__.py
odoo/addons/shopfloor_reception_purchase_partner_ref/i18n/shopfloor_reception_purchase_partner_ref.pot
odoo/addons/shopfloor_reception_purchase_partner_ref/readme/CONTRIBUTORS.rst
odoo/addons/shopfloor_reception_purchase_partner_ref/readme/DESCRIPTION.rst
odoo/addons/shopfloor_reception_purchase_partner_ref/services/__init__.py
odoo/addons/shopfloor_reception_purchase_partner_ref/services/reception.py
odoo/addons/shopfloor_reception_purchase_partner_ref/static/description/icon.png
odoo/addons/shopfloor_reception_purchase_partner_ref/static/description/index.html
odoo/addons/shopfloor_reception_purchase_partner_ref/tests/__init__.py
odoo/addons/shopfloor_reception_purchase_partner_ref/tests/test_data.py
odoo14_addon_shopfloor_reception_purchase_partner_ref-14.0.1.1.0.dist-info/METADATA
odoo14_addon_shopfloor_reception_purchase_partner_ref-14.0.1.1.0.dist-info/WHEEL
odoo14_addon_shopfloor_reception_purchase_partner_ref-14.0.1.1.0.dist-info/top_level.txt
odoo14_addon_shopfloor_reception_purchase_partner_ref-14.0.1.1.0.dist-info/RECORD
