Metadata-Version: 2.1
Name: odoo14-addon-shopfloor-reception-purchase-partner-ref
Version: 14.0.1.1.0
Summary: Adds the purchase partner ref field to shopfloor reception scenario
Home-page: https://github.com/OCA/wms
Author: MT Software, Odoo Community Association (OCA)
Author-email: support@odoo-community.org
License: AGPL-3
Platform: UNKNOWN
Classifier: Programming Language :: Python
Classifier: Framework :: Odoo
Classifier: Framework :: Odoo :: 14.0
Classifier: License :: OSI Approved :: GNU Affero General Public License v3
Requires-Python: >=3.6
Requires-Dist: odoo14-addon-shopfloor-purchase-base
Requires-Dist: odoo14-addon-shopfloor-reception
Requires-Dist: odoo (<14.1dev,>=14.0a)
